setup.cfg
setup.py
yahooscraper/__init__.py
yahooscraper/login.py
yahooscraper.egg-info/PKG-INFO
yahooscraper.egg-info/SOURCES.txt
yahooscraper.egg-info/dependency_links.txt
yahooscraper.egg-info/pbr.json
yahooscraper.egg-info/requires.txt
yahooscraper.egg-info/top_level.txt
yahooscraper/fantasy/__init__.py
yahooscraper/fantasy/team.py