Metadata-Version: 1.1
Name: yahooscraper
Version: 0.3.0
Summary: Utilities for scraping Yahoo pages
Home-page: https://github.com/jbrudvik/yahooscraper
Author: Jeremy Brudvik
Author-email: jeremy@brudvik.me
License: MIT
Keywords: scrape,screen,web,Yahoo,login,fantasy
Platform: UNKNOWN
Classifier: Programming Language :: Python :: 2.7
Classifier: Programming Language :: Python :: 3.4
